dictature/__init__.py
dictature/dictature.py
dictature/backend/__init__.py
dictature/backend/directory.py
dictature/backend/misp.py
dictature/backend/mock.py
dictature/backend/mysql.py
dictature/backend/s3.py
dictature/backend/sqlite.py
dictature/backend/webdav.py
dictature/transformer/__init__.py
dictature/transformer/aes.py
dictature/transformer/gzip.py
dictature/transformer/hmac.py
dictature/transformer/mock.py
dictature/transformer/passthrough.py
dictature/transformer/pipeline.py
dictature-0.14.0.dist-info/LICENSE
dictature-0.14.0.dist-info/METADATA
dictature-0.14.0.dist-info/WHEEL
dictature-0.14.0.dist-info/top_level.txt
dictature-0.14.0.dist-info/RECORD
