Metadata-Version: 2.1
Name: dictature
Version: 0.14.0
Summary: dictature -- A generic wrapper around dict-like interface with mulitple backends
Author-email: Adam Hlavacek <git@adamhlavacek.com>
Project-URL: Homepage, https://github.com/esoadamo/dictature
Project-URL: Issues, https://github.com/esoadamo/dictature/issues
Classifier: Programming Language :: Python :: 3
Classifier: License :: OSI Approved :: MIT License
Classifier: Operating System :: OS Independent
License-File: LICENSE
